COPYING
MANIFEST.in
Makefile
README.md
requirements.txt
setup.py
elasticfun/__init__.py
elasticfun/compat.py
elasticfun/exceptions.py
elasticfun/query.py
elasticfun/queryset.py
elasticfun/wrappers.py
elasticfun.egg-info/PKG-INFO
elasticfun.egg-info/SOURCES.txt
elasticfun.egg-info/dependency_links.txt
elasticfun.egg-info/requires.txt
elasticfun.egg-info/top_level.txt
elasticfun/django/__init__.py