Metadata-Version: 1.1
Name: elasticfun
Version: 0.3.3
Summary: ElasticSearch Query functionality using Django
Home-page: https://github.com/Yipit/elasticfun
Author: Lincoln de Sousa, Nitya Oberoi
Author-email: lincoln@yipit.com, nitya@yipit.com
License: GPL
Platform: UNKNOWN
Classifier: Development Status :: 3 - Alpha
Classifier: Framework :: Django
Classifier: Intended Audience :: Developers
Classifier: License :: OSI Approved :: GNU General Public License v3 or later (GPLv3+)
Classifier: Natural Language :: English
Classifier: Operating System :: Microsoft
Classifier: Operating System :: POSIX
Classifier: Programming Language :: Python
Classifier: Programming Language :: Python :: 2.7
Classifier: Programming Language :: Python :: 3.3
